easysteam/__init__.py
easysteam/store.py
easysteam-1.0.0.dist-info/LICENSE
easysteam-1.0.0.dist-info/METADATA
easysteam-1.0.0.dist-info/WHEEL
easysteam-1.0.0.dist-info/top_level.txt
easysteam-1.0.0.dist-info/RECORD
