Metadata-Version: 2.1
Name: easysteam
Version: 1.0.0
Summary: A third-party API to access steam data and values
Home-page: https://github.com/simpl360/easysteam
License: UNKNOWN
Project-URL: Bug Tracker, https://github.com/simpl360/easysteam/issues
Platform: UNKNOWN
Classifier: Programming Language :: Python :: 3
Classifier: License :: OSI Approved :: GNU General Public License v3 (GPLv3)
Classifier: Operating System :: OS Independent
Requires-Python: >=3.9
License-File: LICENSE
